Workbook

Sheet Sheet6
A3: Row Labels | B3: Count of sales | C3: Count of profit
A4: Maharashtra | B4: 1776 | C4: 1776
A5: Karnataka | B5: 1227 | C5: 1227
A6: Chandigarh | B6: 1186 | C6: 1186
A7: Delhi | B7: 1150 | C7: 1150
A8: Kerala | B8: 1079 | C8: 1079
A9: Tamil Nadu | B9: 1069 | C9: 1069
A10: Gujarat | B10: 1063 | C10: 1063
A11: Telangana | B11: 939 | C11: 939
A12: West Bengal | B12: 872 | C12: 872
A13: Rajasthan | B13: 858 | C13: 858
A14: Uttar Pradesh | B14: 767 | C14: 767
A15: Grand Total | B15: 11986 | C15: 11986

Sheet Sheet5
A3: Row Labels | B3: Count of sales
A4: 2025 | B4: 11986
A5: Jan | B5: 1067
A6: Feb | B6: 899
A7: Mar | B7: 1041
A8: Apr | B8: 982
A9: May | B9: 971
A10: Jun | B10: 979
A11: Jul | B11: 1019
A12: Aug | B12: 965
A13: Sep | B13: 1018
A14: Oct | B14: 1027
A15: Nov | B15: 1007
... A17: Grand Total | B17: 11986

Sheet Sheet8
A3: Row Labels | B3: Count of profit | C3: Count of sales
A4: Consumer | B4: 6702 | C4: 6702
A5: Corporate | B5: 3455 | C5: 3455
A6: Small Business | B6: 1829 | C6: 1829
A7: Grand Total | B7: 11986 | C7: 11986

Sheet Sheet9
A3: Row Labels | B3: Count of sales | C3: Count of profit
A4: P063 | B4: 181 | C4: 181
A5: P005 | B5: 173 | C5: 173
A6: P026 | B6: 173 | C6: 173
A7: P052 | B7: 172 | C7: 172
A8: P038 | B8: 171 | C8: 171
A9: P058 | B9: 169 | C9: 169
A10: P044 | B10: 169 | C10: 169
A11: P032 | B11: 167 | C11: 167
A12: P048 | B12: 165 | C12: 165
A13: P075 | B13: 163 | C13: 163
A14: P053 | B14: 163 | C14: 163
A15: Grand Total | B15: 1866 | C15: 1866

Sheet Dashboard
B2: E-Commerce Sales Analytics Dashboard
B3: Sales, Profit, Customer & Product Performance
B6: Total Orders | C6: Units Sold | D6: Total Sales | E6: Total Profit | F6: Profit Margin
B7: =Sheet3!B2 -> 11985 | C7: =Sheet3!B3 -> 24122 | D7: =Sheet3!B4 -> 4.312538e+08 | E7: =Sheet3!B5 -> 5819150.4 | F7: =Sheet3!B6 -> 0.013493563

Sheet insights
A1: Maharashtra was the highest-performing state by sales.
A2: July recorded the highest monthly sales and profit.
A3: November recorded the lowest monthly sales.
A4: Home Appliances generated the highest category sales.
A5: Fragrance Product 034 had a strong profit margin among high-sales products.
A6: Accessories Product 025 had the lowest margin among products with high sales.
A7: 133 customers were identified as repeat customers in the SQL analysis.
A8: Discount-level profit margins remained relatively stable.

Sheet orders
A1: order_id | B1: order_date | C1: customer_id | D1: product_id | E1: quantity | F1: discount | G1: unit_price | H1: sales | I1: base_margin | J1: profit | K1: Category | L1: State | M1: Customer segement
A2: O000001 | B2: 45867 | C2: C0257 | D2: P013 | E2: 2 | F2: 0.2 | G2: 17633 | H2: 28212.800000000003 | I2: 0.19 | J2: 5507.288722782825 | K2: =_xlfn.XLOOKUP(D2,Products!A:A,Products!C:C,"") -> Home Appliances | L2: =_xlfn.XLOOKUP(C2,Customers!A:A,Customers!D:D,"") -> Delhi | M2: =_xlfn.XLOOKUP(C2,Customers!A:A,Customers!E:E,"") -> Consumer
A3: O000002 | B3: 45961 | C3: C0654 | D3: P032 | E3: 1 | F3: 0.1 | G3: 10888 | H3: 9799.2 | I3: 0.19 | J3: 2266.9387 | K3: =_xlfn.XLOOKUP(D3,Products!A:A,Products!C:C,"") -> Home Appliances | L3: =_xlfn.XLOOKUP(C3,Customers!A:A,Customers!D:D,"") -> Maharashtra | M3: =_xlfn.XLOOKUP(C3,Customers!A:A,Customers!E:E,"") -> Corporate
A4: O000003 | B4: 45953 | C4: C1160 | D4: P027 | E4: 4 | F4: 0.05 | G4: 30563 | H4: 116139.4 | I4: 0.19 | J4: 29980.827828686088 | K4: =_xlfn.XLOOKUP(D4,Products!A:A,Products!C:C,"") -> Home Appliances | L4: =_xlfn.XLOOKUP(C4,Customers!A:A,Customers!D:D,"") -> Telangana | M4: =_xlfn.XLOOKUP(C4,Customers!A:A,Customers!E:E,"") -> Consumer
A5: O000004 | B5: 45754 | C5: C0591 | D5: P051 | E5: 1 | F5: 0.15 | G5: 48370 | H5: 41114.5 | I5: 0.16 | J5: 7104.8769886780665 | K5: =_xlfn.XLOOKUP(D5,Products!A:A,Products!C:C,"") -> Technology | L5: =_xlfn.XLOOKUP(C5,Customers!A:A,Customers!D:D,"") -> West Bengal | M5: =_xlfn.XLOOKUP(C5,Customers!A:A,Customers!E:E,"") -> Consumer
A6: O000005 | B6: 45865 | C6: C0444 | D6: P034 | E6: 2 | F6: 0 | G6: 49003 | H6: 98006 | I6: 0.31 | J6: 28358.475966579732 | K6: =_xlfn.XLOOKUP(D6,Products!A:A,Products!C:C,"") -> Beauty & Personal Care | L6: =_xlfn.XLOOKUP(C6,Customers!A:A,Customers!D:D,"") -> Karnataka | M6: =_xlfn.XLOOKUP(C6,Customers!A:A,Customers!E:E,"") -> Consumer
A7: O000006 | B7: 45794 | C7: C0418 | D7: P028 | E7: 3 | F7: 0.2 | G7: 7879 | H7: 18909.600000000002 | I7: 0.16 | J7: 3354.673069834371 | K7: =_xlfn.XLOOKUP(D7,Products!A:A,Products!C:C,"") -> Technology | L7: =_xlfn.XLOOKUP(C7,Customers!A:A,Customers!D:D,"") -> Telangana | M7: =_xlfn.XLOOKUP(C7,Customers!A:A,Customers!E:E,"") -> Corporate
A8: O000007 | B8: 45841 | C8: C0574 | D8: P073 | E8: 5 | F8: 0.1 | G8: 3110 | H8: 13995 | I8: 0.31 | J8: 3936.8258840192743 | K8: =_xlfn.XLOOKUP(D8,Products!A:A,Products!C:C,"") -> Beauty & Personal Care | L8: =_xlfn.XLOOKUP(C8,Customers!A:A,Customers!D:D,"") -> Telangana | M8: =_xlfn.XLOOKUP(C8,Customers!A:A,Customers!E:E,"") -> Consumer
A9: O000008 | B9: 45733 | C9: C0129 | D9: P072 | E9: 2 | F9: 0.1 | G9: 4623 | H9: 8321.4 | I9: 0.28 | J9: 2691.770663486954 | K9: =_xlfn.XLOOKUP(D9,Products!A:A,Products!C:C,"") -> Office Supplies | L9: =_xlfn.XLOOKUP(C9,Customers!A:A,Customers!D:D,"") -> West Bengal | M9: =_xlfn.XLOOKUP(C9,Customers!A:A,Customers!E:E,"") -> Corporate
A10: O000009 | B10: 45944 | C10: C1011 | D10: P030 | E10: 1 | F10: 0.15 | G10: 26232 | H10: 22297.2 | I10: 0.22 | J10: 4357.815378540655 | K10: =_xlfn.XLOOKUP(D10,Products!A:A,Products!C:C,"") -> Furniture | L10: =_xlfn.XLOOKUP(C10,Customers!A:A,Customers!D:D,"") -> Telangana | M10: =_xlfn.XLOOKUP(C10,Customers!A:A,Customers!E:E,"") -> Consumer
A11: O000010 | B11: 45799 | C11: C0341 | D11: P009 | E11: 1 | F11: 0.15 | G11: 11380 | H11: 9673 | I11: 0.28 | J11: 2643.0513431082604 | K11: =_xlfn.XLOOKUP(D11,Products!A:A,Products!C:C,"") -> Office Supplies | L11: =_xlfn.XLOOKUP(C11,Customers!A:A,Customers!D:D,"") -> Delhi | M11: =_xlfn.XLOOKUP(C11,Customers!A:A,Customers!E:E,"") -> Corporate
A12: O000011 | B12: 45894 | C12: C0810 | D12: P013 | E12: 1 | F12: 0.05 | G12: 17633 | H12: 16751.35 | I12: 0.19 | J12: 2691.6291116790394 | K12: =_xlfn.XLOOKUP(D12,Products!A:A,Products!C:C,"") -> Home Appliances | L12: =_xlfn.XLOOKUP(C12,Customers!A:A,Customers!D:D,"") -> Delhi | M12: =_xlfn.XLOOKUP(C12,Customers!A:A,Customers!E:E,"") -> Consumer
A13: O000012 | B13: 45682 | C13: C0992 | D13: P064 | E13: 2 | F13: 0.25 | G13: 9427 | H13: 14140.5 | I13: 0.22 | J13: 3201.0707372621523 | K13: =_xlfn.XLOOKUP(D13,Products!A:A,Products!C:C,"") -> Furniture | L13: =_xlfn.XLOOKUP(C13,Customers!A:A,Customers!D:D,"") -> Tamil Nadu | M13: =_xlfn.XLOOKUP(C13,Customers!A:A,Customers!E:E,"") -> Consumer
A14: O000013 | B14: 45947 | C14: C0100 | D14: P038 | E14: 3 | F14: 0.25 | G14: 9257 | H14: 20828.25 | I14: 0.16 | J14: 3491.0417295438915 | K14: =_xlfn.XLOOKUP(D14,Products!A:A,Products!C:C,"") -> Technology | L14: =_xlfn.XLOOKUP(C14,Customers!A:A,Customers!D:D,"") -> Karnataka | M14: =_xlfn.XLOOKUP(C14,Customers!A:A,Customers!E:E,"") -> Consumer
A15: O000014 | B15: 45724 | C15: C0039 | D15: P022 | E15: 3 | F15: 0.1 | G15: 5299 | H15: 14307.300000000001 | I15: 0.16 | J15: 2661.0520461352435 | K15: =_xlfn.XLOOKUP(D15,Products!A:A,Products!C:C,"") -> Technology | L15: =_xlfn.XLOOKUP(C15,Customers!A:A,Customers!D:D,"") -> Delhi | M15: =_xlfn.XLOOKUP(C15,Customers!A:A,Customers!E:E,"") -> Corporate
A16: O000015 | B16: 45907 | C16: C0263 | D16: P031 | E16: 1 | F16: 0.1 | G16: 41060 | H16: 36954 | I16: 0.28 | J16: 10501.864009486873 | K16: =_xlfn.XLOOKUP(D16,Products!A:A,Products!C:C,"") -> Office Supplies | L16: =_xlfn.XLOOKUP(C16,Customers!A:A,Customers!D:D,"") -> Kerala | M16: =_xlfn.XLOOKUP(C16,Customers!A:A,Customers!E:E,"") -> Corporate
A17: O000016 | B17: 45775 | C17: C0150 | D17: P042 | E17: 2 | F17: 0.1 | G17: 24549 | H17: 44188.200000000004 | I17: 0.19 | J17: 8467.314014490421 | K17: =_xlfn.XLOOKUP(D17,Products!A:A,Products!C:C,"") -> Home Appliances | L17: =_xlfn.XLOOKUP(C17,Customers!A:A,Customers!D:D,"") -> Kerala | M17: =_xlfn.XLOOKUP(C17,Customers!A:A,Customers!E:E,"") -> Consumer
A18: O000017 | B18: 45730 | C18: C0690 | D18: P062 | E18: 4 | F18: 0.1 | G18: 40809 | H18: 146912.4 | I18: 0.19 | J18: 24962.502461561904 | K18: =_xlfn.XLOOKUP(D18,Products!A:A,Products!C:C,"") -> Home Appliances | L18: =_xlfn.XLOOKUP(C18,Customers!A:A,Customers!D:D,"") -> West Bengal | M18: =_xlfn.XLOOKUP(C18,Customers!A:A,Customers!E:E,"") -> Small Business
A19: O000018 | B19: 45939 | C19: C0813 | D19: P064 | E19: 4 | F19: 0.25 | G19: 9427 | H19: 28281 | I19: 0.22 | J19: 5938.383410973606 | K19: =_xlfn.XLOOKUP(D19,Products!A:A,Products!C:C,"") -> Furniture | L19: =_xlfn.XLOOKUP(C19,Customers!A:A,Customers!D:D,"") -> Karnataka | M19: =_xlfn.XLOOKUP(C19,Customers!A:A,Customers!E:E,"") -> Consumer
A20: O000019 | B20: 46017 | C20: C1144 | D20: P074 | E20: 2 | F20: 0.05 | G20: 28518 | H20: 54184.2 | I20: 0.31 | J20: 14155.516355946893 | K20: =_xlfn.XLOOKUP(D20,Products!A:A,Products!C:C,"") -> Beauty & Personal Care | L20: =_xlfn.XLOOKUP(C20,Customers!A:A,Customers!D:D,"") -> Tamil Nadu | M20: =_xlfn.XLOOKUP(C20,Customers!A:A,Customers!E:E,"") -> Corporate
A21: O000020 | B21: 45667 | C21: C0219 | D21: P009 | E21: 2 | F21: 0 | G21: 11380 | H21: 22760 | I21: 0.28 | J21: 7483.022143328183 | K21: =_xlfn.XLOOKUP(D21,Products!A:A,Products!C:C,"") -> Office Supplies | L21: =_xlfn.XLOOKUP(C21,Customers!A:A,Customers!D:D,"") -> Gujarat | M21: =_xlfn.XLOOKUP(C21,Customers!A:A,Customers!E:E,"") -> Consumer
A22: O000021 | B22: 45868 | C22: C0906 | D22: P044 | E22: 2 | F22: 0.2 | G22: 41116 | H22: 65785.6 | I22: 0.19 | J22: 12282.134430992155 | K22: =_xlfn.XLOOKUP(D22,Products!A:A,Products!C:C,"") -> Home Appliances | L22: =_xlfn.XLOOKUP(C22,Customers!A:A,Customers!D:D,"") -> Maharashtra | M22: =_xlfn.XLOOKUP(C22,Customers!A:A,Customers!E:E,"") -> Consumer
A23: O000022 | B23: 45980 | C23: C1147 | D23: P063 | E23: 1 | F23: 0.05 | G23: 11537 | H23: 10960.15 | I23: 0.22 | J23: 3040.612764819357 | K23: =_xlfn.XLOOKUP(D23,Products!A:A,Products!C:C,"") -> Furniture | L23: =_xlfn.XLOOKUP(C23,Customers!A:A,Customers!D:D,"") -> Karnataka | M23: =_xlfn.XLOOKUP(C23,Customers!A:A,Customers!E:E,"") -> Consumer
A24: O000023 | B24: 45809 | C24: C0244 | D24: P040 | E24: 1 | F24: 0.15 | G24: 43459 | H24: 36940.15 | I24: 0.19 | J24: 6862.1494091139675 | K24: =_xlfn.XLOOKUP(D24,Products!A:A,Products!C:C,"") -> Home Appliances | L24: =_xlfn.XLOOKUP(C24,Customers!A:A,Customers!D:D,"") -> Maharashtra | M24: =_xlfn.XLOOKUP(C24,Customers!A:A,Customers!E:E,"") -> Corporate
A25: O000024 | B25: 45662 | C25: C0886 | D25: P041 | E25: 2 | F25: 0.05 | G25: 40096 | H25: 76182.4 | I25: 0.22 | J25: 11688.334150953106 | K25: =_xlfn.XLOOKUP(D25,Products!A:A,Products!C:C,"") -> Furniture | L25: =_xlfn.XLOOKUP(C25,Customers!A:A,Customers!D:D,"") -> Gujarat | M25: =_xlfn.XLOOKUP(C25,Customers!A:A,Customers!E:E,"") -> Consumer
A26: O000025 | B26: 45852 | C26: C0587 | D26: P072 | E26: 1 | F26: 0.25 | G26: 4623 | H26: 3467.25 | I26: 0.28 | J26: 916.1730085386442 | K26: =_xlfn.XLOOKUP(D26,Products!A:A,Products!C:C,"") -> Office Supplies | L26: =_xlfn.XLOOKUP(C26,Customers!A:A,Customers!D:D,"") -> Maharashtra | M26: =_xlfn.XLOOKUP(C26,Customers!A:A,Customers!E:E,"") -> Consumer
A27: O000026 | B27: 45940 | C27: C0518 | D27: P050 | E27: 2 | F27: 0.15 | G27: 22075 | H27: 37527.5 | I27: 0.16 | J27: 6000.976813307517 | K27: =_xlfn.XLOOKUP(D27,Products!A:A,Products!C:C,"") -> Technology | L27: =_xlfn.XLOOKUP(C27,Customers!A:A,Customers!D:D,"") -> Telangana | M27: =_xlfn.XLOOKUP(C27,Customers!A:A,Customers!E:E,"") -> Consumer
A28: O000027 | B28: 45770 | C28: C1045 | D28: P020 | E28: 2 | F28: 0.2 | G28: 10792 | H28: 17267.2 | I28: 0.28 | J28: 4874.310621806567 | K28: =_xlfn.XLOOKUP(D28,Products!A:A,Products!C:C,"") -> Office Supplies | L28: =_xlfn.XLOOKUP(C28,Customers!A:A,Customers!D:D,"") -> Maharashtra | M28: =_xlfn.XLOOKUP(C28,Customers!A:A,Customers!E:E,"") -> Consumer
A29: O000028 | B29: 45928 | C29: C0190 | D29: P070 | E29: 2 | F29: 0.25 | G29: 40034 | H29: 60051 | I29: 0.28 | J29: 18236.846330652035 | K29: =_xlfn.XLOOKUP(D29,Products!A:A,Products!C:C,"") -> Office Supplies | L29: =_xlfn.XLOOKUP(C29,Customers!A:A,Customers!D:D,"") -> Rajasthan | M29: =_xlfn.XLOOKUP(C29,Customers!A:A,Customers!E:E,"") -> Consumer
... A31: O000030 | B31: 45762 | C31: C0615 | D31: P033 | E31: 1 | F31: 0.1 | G31: 13614 | H31: 12252.6 | I31: 0.19 | J31: 2183.476185384776 | K31: =_xlfn.XLOOKUP(D31,Products!A:A,Products!C:C,"") -> Home Appliances | L31: =_xlfn.XLOOKUP(C31,Customers!A:A,Customers!D:D,"") -> Chandigarh | M31: =_xlfn.XLOOKUP(C31,Customers!A:A,Customers!E:E,"") -> Consumer
A32: O000031 | B32: 45838 | C32: C0856 | D32: P063 | E32: 1 | F32: 0.15 | G32: 11537 | H32: 9806.449999999999 | I32: 0.22 | J32: 1843.370973167945 | K32: =_xlfn.XLOOKUP(D32,Products!A:A,Products!C:C,"") -> Furniture | L32: =_xlfn.XLOOKUP(C32,Customers!A:A,Customers!D:D,"") -> Gujarat | M32: =_xlfn.XLOOKUP(C32,Customers!A:A,Customers!E:E,"") -> Consumer
A33: O000032 | B33: 45701 | C33: C0466 | D33: P057 | E33: 1 | F33: 0.15 | G33: 42988 | H33: 36539.799999999996 | I33: 0.19 | J33: 6422.860349918301 | K33: =_xlfn.XLOOKUP(D33,Products!A:A,Products!C:C,"") -> Home Appliances | L33: =_xlfn.XLOOKUP(C33,Customers!A:A,Customers!D:D,"") -> Chandigarh | M33: =_xlfn.XLOOKUP(C33,Customers!A:A,Customers!E:E,"") -> Consumer
A34: O000033 | B34: 45939 | C34: C0099 | D34: P065 | E34: 5 | F34: 0.05 | G34: 7732 | H34: 36727 | I34: 0.22 | J34: 8857.0247 | K34: =_xlfn.XLOOKUP(D34,Products!A:A,Products!C:C,"") -> Furniture | L34: =_xlfn.XLOOKUP(C34,Customers!A:A,Customers!D:D,"") -> Rajasthan | M34: =_xlfn.XLOOKUP(C34,Customers!A:A,Customers!E:E,"") -> Small Business
A35: O000034 | B35: 45832 | C35: C0830 | D35: P052 | E35: 1 | F35: 0.2 | G35: 38016 | H35: 30412.800000000003 | I35: 0.16 | J35: 5779.7836913779165 | K35: =_xlfn.XLOOKUP(D35,Products!A:A,Products!C:C,"") -> Technology | L35: =_xlfn.XLOOKUP(C35,Customers!A:A,Customers!D:D,"") -> Chandigarh | M35: =_xlfn.XLOOKUP(C35,Customers!A:A,Customers!E:E,"") -> Corporate
A36: O000035 | B36: 45819 | C36: C0997 | D36: P006 | E36: 1 | F36: 0.05 | G36: 14233 | H36: 13521.349999999999 | I36: 0.22 | J36: 2655.7960212909898 | K36: =_xlfn.XLOOKUP(D36,Products!A:A,Products!C:C,"") -> Furniture | L36: =_xlfn.XLOOKUP(C36,Customers!A:A,Customers!D:D,"") -> Tamil Nadu | M36: =_xlfn.XLOOKUP(C36,Customers!A:A,Customers!E:E,"") -> Corporate
A37: O000036 | B37: 46008 | C37: C1107 | D37: P007 | E37: 1 | F37: 0.2 | G37: 32777 | H37: 26221.600000000002 | I37: 0.19 | J37: 5906.281039668003 | K37: =_xlfn.XLOOKUP(D37,Products!A:A,Products!C:C,"") -> Home Appliances | L37: =_xlfn.XLOOKUP(C37,Customers!A:A,Customers!D:D,"") -> Maharashtra | M37: =_xlfn.XLOOKUP(C37,Customers!A:A,Customers!E:E,"") -> Corporate
A38: O000037 | B38: 45997 | C38: C0056 | D38: P009 | E38: 2 | F38: 0.1 | G38: 11380 | H38: 20484 | I38: 0.28 | J38: 6143.504797086506 | K38: =_xlfn.XLOOKUP(D38,Products!A:A,Products!C:C,"") -> Office Supplies | L38: =_xlfn.XLOOKUP(C38,Customers!A:A,Customers!D:D,"") -> Kerala | M38: =_xlfn.XLOOKUP(C38,Customers!A:A,Customers!E:E,"") -> Corporate
A39: O000038 | B39: 45797 | C39: C1046 | D39: P061 | E39: 2 | F39: 0.1 | G39: 37834 | H39: 68101.2 | I39: 0.28 | J39: 16953.93354887509 | K39: =_xlfn.XLOOKUP(D39,Products!A:A,Products!C:C,"") -> Office Supplies | L39: =_xlfn.XLOOKUP(C39,Customers!A:A,Customers!D:D,"") -> Tamil Nadu | M39: =_xlfn.XLOOKUP(C39,Customers!A:A,Customers!E:E,"") -> Consumer
A40: O000039 | B40: 45789 | C40: C0580 | D40: P080 | E40: 1 | F40: 0.05 | G40: 657 | H40: 624.15 | I40: 0.22 | J40: 142.70233350567122 | K40: =_xlfn.XLOOKUP(D40,Products!A:A,Products!C:C,"") -> Furniture | L40: =_xlfn.XLOOKUP(C40,Customers!A:A,Customers!D:D,"") -> Tamil Nadu | M40: =_xlfn.XLOOKUP(C40,Customers!A:A,Customers!E:E,"") -> Corporate
A41: O000040 | B41: 45744 | C41: C0185 | D41: P034 | E41: 4 | F41: 0 | G41: 49003 | H41: 196012 | I41: 0.31 | J41: 63300.47735429711 | K41: =_xlfn.XLOOKUP(D41,Products!A:A,Products!C:C,"") -> Beauty & Personal Care | L41: =_xlfn.XLOOKUP(C41,Customers!A:A,Customers!D:D,"") -> Karnataka | M41: =_xlfn.XLOOKUP(C41,Customers!A:A,Customers!E:E,"") -> Consumer
A42: O000041 | B42: 45833 | C42: C0522 | D42: P035 | E42: 3 | F42: 0.05 | G42: 3648 | H42: 10396.8 | I42: 0.22 | J42: 1899.9580379521449 | K42: =_xlfn.XLOOKUP(D42,Products!A:A,Products!C:C,"") -> Furniture | L42: =_xlfn.XLOOKUP(C42,Customers!A:A,Customers!D:D,"") -> Kerala | M42: =_xlfn.XLOOKUP(C42,Customers!A:A,Customers!E:E,"") -> Corporate
A43: O000042 | B43: 45840 | C43: C0264 | D43: P020 | E43: 1 | F43: 0.1 | G43: 10792 | H43: 9712.800000000001 | I43: 0.28 | J43: 2257.717855843792 | K43: =_xlfn.XLOOKUP(D43,Products!A:A,Products!C:C,"") -> Office Supplies | L43: =_xlfn.XLOOKUP(C43,Customers!A:A,Customers!D:D,"") -> Delhi | M43: =_xlfn.XLOOKUP(C43,Customers!A:A,Customers!E:E,"") -> Corporate
A44: O000043 | B44: 45786 | C44: C1062 | D44: P058 | E44: 2 | F44: 0.1 | G44: 5109 | H44: 9196.2 | I44: 0.19 | J44: 1899.7847146869967 | K44: =_xlfn.XLOOKUP(D44,Products!A:A,Products!C:C,"") -> Home Appliances | L44: =_xlfn.XLOOKUP(C44,Customers!A:A,Customers!D:D,"") -> Maharashtra | M44: =_xlfn.XLOOKUP(C44,Customers!A:A,Customers!E:E,"") -> Consumer
A45: O000044 | B45: 45903 | C45: C1003 | D45: P060 | E45: 2 | F45: 0.15 | G45: 1533 | H45: 2606.1 | I45: 0.16 | J45: 375.53989717357956 | K45: =_xlfn.XLOOKUP(D45,Products!A:A,Products!C:C,"") -> Technology | L45: =_xlfn.XLOOKUP(C45,Customers!A:A,Customers!D:D,"") -> Gujarat | M45: =_xlfn.XLOOKUP(C45,Customers!A:A,Customers!E:E,"") -> Corporate
A46: O000045 | B46: 45746 | C46: C0123 | D46: P054 | E46: 1 | F46: 0.05 | G46: 24562 | H46: 23333.899999999998 | I46: 0.22 | J46: 6368.3710536197295 | K46: =_xlfn.XLOOKUP(D46,Products!A:A,Products!C:C,"") -> Furniture | L46: =_xlfn.XLOOKUP(C46,Customers!A:A,Customers!D:D,"") -> West Bengal | M46: =_xlfn.XLOOKUP(C46,Customers!A:A,Customers!E:E,"") -> Corporate
A47: O000046 | B47: 45723 | C47: C1180 | D47: P035 | E47: 3 | F47: 0.1 | G47: 3648 | H47: 9849.6 | I47: 0.22 | J47: 2760.2255045282063 | K47: =_xlfn.XLOOKUP(D47,Products!A:A,Products!C:C,"") -> Furniture | L47: =_xlfn.XLOOKUP(C47,Customers!A:A,Customers!D:D,"") -> Maharashtra | M47: =_xlfn.XLOOKUP(C47,Customers!A:A,Customers!E:E,"") -> Corporate
A48: O000047 | B48: 45815 | C48: C0301 | D48: P047 | E48: 1 | F48: 0.2 | G48: 29812 | H48: 23849.600000000002 | I48: 0.28 | J48: 7071.874451227457 | K48: =_xlfn.XLOOKUP(D48,Products!A:A,Products!C:C,"") -> Office Supplies | L48: =_xlfn.XLOOKUP(C48,Customers!A:A,Customers!D:D,"") -> Delhi | M48: =_xlfn.XLOOKUP(C48,Customers!A:A,Customers!E:E,"") -> Consumer
A49: O000048 | B49: 45806 | C49: C0833 | D49: P046 | E49: 1 | F49: 0.15 | G49: 28530 | H49: 24250.5 | I49: 0.16 | J49: 4687.886071073855 | K49: =_xlfn.XLOOKUP(D49,Products!A:A,Products!C:C,"") -> Technology | L49: =_xlfn.XLOOKUP(C49,Customers!A:A,Customers!D:D,"") -> Rajasthan | M49: =_xlfn.XLOOKUP(C49,Customers!A:A,Customers!E:E,"") -> Consumer
A50: O000049 | B50: 45997 | C50: C1091 | D50: P004 | E50: 2 | F50: 0 | G50: 19940 | H50: 39880 | I50: 0.16 | J50: 4951.705359286896 | K50: =_xlfn.XLOOKUP(D50,Products!A:A,Products!C:C,"") -> Technology | L50: =_xlfn.XLOOKUP(C50,Customers!A:A,Customers!D:D,"") -> Gujarat | M50: =_xlfn.XLOOKUP(C50,Customers!A:A,Customers!E:E,"") -> Consumer
A51: O000050 | B51: 45773 | C51: C0645 | D51: P010 | E51: 2 | F51: 0.2 | G51: 46436 | H51: 74297.6 | I51: 0.28 | J51: 17339.842547226257 | K51: =_xlfn.XLOOKUP(D51,Products!A:A,Products!C:C,"") -> Office Supplies | L51: =_xlfn.XLOOKUP(C51,Customers!A:A,Customers!D:D,"") -> Kerala | M51: =_xlfn.XLOOKUP(C51,Customers!A:A,Customers!E:E,"") -> Consumer
A52: O000051 | B52: 45871 | C52: C0874 | D52: P075 | E52: 3 | F52: 0.25 | G52: 13000 | H52: 29250 | I52: 0.19 | J52: 5412.727098029293 | K52: =_xlfn.XLOOKUP(D52,Products!A:A,Products!C:C,"") -> Home Appliances | L52: =_xlfn.XLOOKUP(C52,Customers!A:A,Customers!D:D,"") -> Maharashtra | M52: =_xlfn.XLOOKUP(C52,Customers!A:A,Customers!E:E,"") -> Corporate
A53: O000052 | B53: 45951 | C53: C0394 | D53: P040 | E53: 1 | F53: 0.2 | G53: 43459 | H53: 34767.200000000004 | I53: 0.19 | J53: 5040.214175055837 | K53: =_xlfn.XLOOKUP(D53,Products!A:A,Products!C:C,"") -> Home Appliances | L53: =_xlfn.XLOOKUP(C53,Customers!A:A,Customers!D:D,"") -> Maharashtra | M53: =_xlfn.XLOOKUP(C53,Customers!A:A,Customers!E:E,"") -> Consumer
A54: O000053 | B54: 45910 | C54: C0661 | D54: P055 | E54: 1 | F54: 0.2 | G54: 38513 | H54: 30810.4 | I54: 0.19 | J54: 6185.721430172254 | K54: =_xlfn.XLOOKUP(D54,Products!A:A,Products!C:C,"") -> Home Appliances | L54: =_xlfn.XLOOKUP(C54,Customers!A:A,Customers!D:D,"") -> Delhi | M54: =_xlfn.XLOOKUP(C54,Customers!A:A,Customers!E:E,"") -> Consumer
A55: O000054 | B55: 45800 | C55: C1155 | D55: P073 | E55: 2 | F55: 0.1 | G55: 3110 | H55: 5598 | I55: 0.31 | J55: 1581.834288699442 | K55: =_xlfn.XLOOKUP(D55,Products!A:A,Products!C:C,"") -> Beauty & Personal Care | L55: =_xlfn.XLOOKUP(C55,Customers!A:A,Customers!D:D,"") -> Karnataka | M55: =_xlfn.XLOOKUP(C55,Customers!A:A,Customers!E:E,"") -> Consumer
A56: O000055 | B56: 45907 | C56: C0069 | D56: P040 | E56: 1 | F56: 0.05 | G56: 43459 | H56: 41286.049999999996 | I56: 0.19 | J56: 8119.560378965799 | K56: =_xlfn.XLOOKUP(D56,Products!A:A,Products!C:C,"") -> Home Appliances | L56: =_xlfn.XLOOKUP(C56,Customers!A:A,Customers!D:D,"") -> Telangana | M56: =_xlfn.XLOOKUP(C56,Customers!A:A,Customers!E:E,"") -> Small Business
A57: O000056 | B57: 45959 | C57: C0762 | D57: P076 | E57: 1 | F57: 0.15 | G57: 36976 | H57: 31429.6 | I57: 0.28 | J57: 8609.869658363381 | K57: =_xlfn.XLOOKUP(D57,Products!A:A,Products!C:C,"") -> Office Supplies | L57: =_xlfn.XLOOKUP(C57,Customers!A:A,Customers!D:D,"") -> Rajasthan | M57: =_xlfn.XLOOKUP(C57,Customers!A:A,Customers!E:E,"") -> Corporate
A58: O000057 | B58: 45682 | C58: C0320 | D58: P023 | E58: 2 | F58: 0.15 | G58: 21121 | H58: 35905.7 | I58: 0.19 | J58: 7623.0434074595505 | K58: =_xlfn.XLOOKUP(D58,Products!A:A,Products!C:C,"") -> Home Appliances | L58: =_xlfn.XLOOKUP(C58,Customers!A:A,Customers!D:D,"") -> Rajasthan | M58: =_xlfn.XLOOKUP(C58,Customers!A:A,Customers!E:E,"") -> Corporate
A59: O000058 | B59: 45934 | C59: C0177 | D59: P015 | E59: 1 | F59: 0.05 | G59: 35247 | H59: 33484.65 | I59: 0.16 | J59: 5740.0009 | K59: =_xlfn.XLOOKUP(D59,Products!A:A,Products!C:C,"") -> Technology | L59: =_xlfn.XLOOKUP(C59,Customers!A:A,Customers!D:D,"") -> Telangana | M59: =_xlfn.XLOOKUP(C59,Customers!A:A,Customers!E:E,"") -> Consumer
A60: O000059 | B60: 45727 | C60: C0584 | D60: P005 | E60: 1 | F60: 0.05 | G60: 14854 | H60: 14111.3 | I60: 0.22 | J60: 2904.990178264145 | K60: =_xlfn.XLOOKUP(D60,Products!A:A,Products!C:C,"") -> Furniture | L60: =_xlfn.XLOOKUP(C60,Customers!A:A,Customers!D:D,"") -> Karnataka | M60: =_xlfn.XLOOKUP(C60,Customers!A:A,Customers!E:E,"") -> Consumer
A61: O000060 | B61: 45770 | C61: C1184 | D61: P040 | E61: 1 | F61: 0.1 | G61: 43459 | H61: 39113.1 | I61: 0.19 | J61: 5558.225812485251 | K61: =_xlfn.XLOOKUP(D61,Products!A:A,Products!C:C,"") -> Home Appliances | L61: =_xlfn.XLOOKUP(C61,Customers!A:A,Customers!D:D,"") -> Kerala | M61: =_xlfn.XLOOKUP(C61,Customers!A:A,Customers!E:E,"") -> Consumer
A62: O000061 | B62: 46020 | C62: C0582 | D62: P018 | E62: 1 | F62: 0.15 | G62: 4101 | H62: 3485.85 | I62: 0.16 | J62: 577.5630636441044 | K62: =_xlfn.XLOOKUP(D62,Products!A:A,Products!C:C,"") -> Technology | L62: =_xlfn.XLOOKUP(C62,Customers!A:A,Customers!D:D,"") -> Gujarat | M62: =_xlfn.XLOOKUP(C62,Customers!A:A,Customers!E:E,"") -> Consumer
A63: O000062 | B63: 45769 | C63: C1159 | D63: P021 | E63: 2 | F63: 0.05 | G63: 13190 | H63: 25061 | I63: 0.22 | J63: 3985.0328393267164 | K63: =_xlfn.XLOOKUP(D63,Products!A:A,Products!C:C,"") -> Furniture | L63: =_xlfn.XLOOKUP(C63,Customers!A:A,Customers!D:D,"") -> Gujarat | M63: =_xlfn.XLOOKUP(C63,Customers!A:A,Customers!E:E,"") -> Small Business
A64: O000063 | B64: 46021 | C64: C0111 | D64: P079 | E64: 1 | F64: 0.1 | G64: 19803 | H64: 17822.7 | I64: 0.16 | J64: 3628.9466373914092 | K64: =_xlfn.XLOOKUP(D64,Products!A:A,Products!C:C,"") -> Technology | L64: =_xlfn.XLOOKUP(C64,Customers!A:A,Customers!D:D,"") -> Karnataka | M64: =_xlfn.XLOOKUP(C64,Customers!A:A,Customers!E:E,"") -> Consumer
A65: O000064 | B65: 45960 | C65: C0999 | D65: P003 | E65: 5 | F65: 0.2 | G65: 2649 | H65: 10596 | I65: 0.16 | J65: 1891.5204930216044 | K65: =_xlfn.XLOOKUP(D65,Products!A:A,Products!C:C,"") -> Technology | L65: =_xlfn.XLOOKUP(C65,Customers!A:A,Customers!D:D,"") -> Maharashtra | M65: =_xlfn.XLOOKUP(C65,Customers!A:A,Customers!E:E,"") -> Corporate
A66: O000065 | B66: 45748 | C66: C0758 | D66: P046 | E66: 1 | F66: 0.05 | G66: 28530 | H66: 27103.5 | I66: 0.16 | J66: 5136.034921699301 | K66: =_xlfn.XLOOKUP(D66,Products!A:A,Products!C:C,"") -> Technology | L66: =_xlfn.XLOOKUP(C66,Customers!A:A,Customers!D:D,"") -> Maharashtra | M66: =_xlfn.XLOOKUP(C66,Customers!A:A,Customers!E:E,"") -> Corporate
A67: O000066 | B67: 45675 | C67: C0283 | D67: P079 | E67: 2 | F67: 0.25 | G67: 19803 | H67: 29704.5 | I67: 0.16 | J67: 3744.788653639324 | K67: =_xlfn.XLOOKUP(D67,Products!A:A,Products!C:C,"") -> Technology | L67: =_xlfn.XLOOKUP(C67,Customers!A:A,Customers!D:D,"") -> Delhi | M67: =_xlfn.XLOOKUP(C67,Customers!A:A,Customers!E:E,"") -> Corporate
A68: O000067 | B68: 45806 | C68: C0194 | D68: P053 | E68: 3 | F68: 0.1 | G68: 44505 | H68: 120163.5 | I68: 0.19 | J68: 24328.64331502465 | K68: =_xlfn.XLOOKUP(D68,Products!A:A,Products!C:C,"") -> Home Appliances | L68: =_xlfn.XLOOKUP(C68,Customers!A:A,Customers!D:D,"") -> Gujarat | M68: =_xlfn.XLOOKUP(C68,Customers!A:A,Customers!E:E,"") -> Consumer
A69: O000068 | B69: 45884 | C69: C0967 | D69: P020 | E69: 1 | F69: 0 | G69: 10792 | H69: 10792 | I69: 0.28 | J69: 2769.9707881996897 | K69: =_xlfn.XLOOKUP(D69,Products!A:A,Products!C:C,"") -> Office Supplies | L69: =_xlfn.XLOOKUP(C69,Customers!A:A,Customers!D:D,"") -> Rajasthan | M69: =_xlfn.XLOOKUP(C69,Customers!A:A,Customers!E:E,"") -> Consumer
A70: O000069 | B70: 45871 | C70: C1071 | D70: P059 | E70: 3 | F70: 0 | G70: 23506 | H70: 70518 | I70: 0.31 | J70: 22228.503431197278 | K70: =_xlfn.XLOOKUP(D70,Products!A:A,Products!C:C,"") -> Beauty & Personal Care | L70: =_xlfn.XLOOKUP(C70,Customers!A:A,Customers!D:D,"") -> Maharashtra | M70: =_xlfn.XLOOKUP(C70,Customers!A:A,Customers!E:E,"") -> Consumer
A71: O000070 | B71: 46017 | C71: C0978 | D71: P021 | E71: 3 | F71: 0.05 | G71: 13190 | H71: 37591.5 | I71: 0.22 | J71: 6956.485087995826 | K71: =_xlfn.XLOOKUP(D71,Products!A:A,Products!C:C,"") -> Furniture | L71: =_xlfn.XLOOKUP(C71,Customers!A:A,Customers!D:D,"") -> Karnataka | M71: =_xlfn.XLOOKUP(C71,Customers!A:A,Customers!E:E,"") -> Small Business
... A75: O000074 | B75: 45899 | C75: C0903 | D75: P010 | E75: 1 | F75: 0.2 | G75: 46436 | H75: 37148.8 | I75: 0.28 | J75: 8263.625715673134 | K75: =_xlfn.XLOOKUP(D75,Products!A:A,Products!C:C,"") -> Office Supplies | L75: =_xlfn.XLOOKUP(C75,Customers!A:A,Customers!D:D,"") -> Kerala | M75: =_xlfn.XLOOKUP(C75,Customers!A:A,Customers!E:E,"") -> Small Business
A76: O000075 | B76: 45795 | C76: C0131 | D76: P067 | E76: 3 | F76: 0.1 | G76: 31519 | H76: 85101.3 | I76: 0.19 | J76: 21373.105 | K76: =_xlfn.XLOOKUP(D76,Products!A:A,Products!C:C,"") -> Home Appliances | L76: =_xlfn.XLOOKUP(C76,Customers!A:A,Customers!D:D,"") -> Gujarat | M76: =_xlfn.XLOOKUP(C76,Customers!A:A,Customers!E:E,"") -> Consumer
A77: O000076 | B77: 46002 | C77: C0814 | D77: P009 | E77: 1 | F77: 0.1 | G77: 11380 | H77: 10242 | I77: 0.28 | J77: 2925.260375714606 | K77: =_xlfn.XLOOKUP(D77,Products!A:A,Products!C:C,"") -> Office Supplies | L77: =_xlfn.XLOOKUP(C77,Customers!A:A,Customers!D:D,"") -> Gujarat | M77: =_xlfn.XLOOKUP(C77,Customers!A:A,Customers!E:E,"") -> Corporate
A78: O000077 | B78: 45837 | C78: C0061 | D78: P029 | E78: 2 | F78: 0.05 | G78: 15711 | H78: 29850.899999999998 | I78: 0.19 | J78: 5677.605584738705 | K78: =_xlfn.XLOOKUP(D78,Products!A:A,Products!C:C,"") -> Home Appliances | L78: =_xlfn.XLOOKUP(C78,Customers!A:A,Customers!D:D,"") -> Telangana | M78: =_xlfn.XLOOKUP(C78,Customers!A:A,Customers!E:E,"") -> Corporate
A79: O000078 | B79: 45857 | C79: C0164 | D79: P037 | E79: 3 | F79: 0.1 | G79: 3506 | H79: 9466.2 | I79: 0.19 | J79: 2022.567195440284 | K79: =_xlfn.XLOOKUP(D79,Products!A:A,Products!C:C,"") -> Home Appliances | L79: =_xlfn.XLOOKUP(C79,Customers!A:A,Customers!D:D,"") -> Uttar Pradesh | M79: =_xlfn.XLOOKUP(C79,Customers!A:A,Customers!E:E,"") -> Consumer
A80: O000079 | B80: 45860 | C80: C0272 | D80: P071 | E80: 4 | F80: 0.1 | G80: 23441 | H80: 84387.6 | I80: 0.19 | J80: 12196.05555074669 | K80: =_xlfn.XLOOKUP(D80,Products!A:A,Products!C:C,"") -> Home Appliances | L80: =_xlfn.XLOOKUP(C80,Customers!A:A,Customers!D:D,"") -> West Bengal | M80: =_xlfn.XLOOKUP(C80,Customers!A:A,Customers!E:E,"") -> Consumer
A81: O000080 | B81: 45718 | C81: C0133 | D81: P038 | E81: 2 | F81: 0.1 | G81: 9257 | H81: 16662.600000000002 | I81: 0.16 | J81: 2210.6890628626347 | K81: =_xlfn.XLOOKUP(D81,Products!A:A,Products!C:C,"") -> Technology | L81: =_xlfn.XLOOKUP(C81,Customers!A:A,Customers!D:D,"") -> Delhi | M81: =_xlfn.XLOOKUP(C81,Customers!A:A,Customers!E:E,"") -> Consumer
A82: O000081 | B82: 45849 | C82: C0998 | D82: P072 | E82: 5 | F82: 0.2 | G82: 4623 | H82: 18492 | I82: 0.28 | J82: 5521.472533430367 | K82: =_xlfn.XLOOKUP(D82,Products!A:A,Products!C:C,"") -> Office Supplies | L82: =_xlfn.XLOOKUP(C82,Customers!A:A,Customers!D:D,"") -> Maharashtra | M82: =_xlfn.XLOOKUP(C82,Customers!A:A,Customers!E:E,"") -> Consumer
A83: O000082 | B83: 45662 | C83: C0038 | D83: P059 | E83: 1 | F83: 0.15 | G83: 23506 | H83: 19980.1 | I83: 0.31 | J83: 6306.736812260512 | K83: =_xlfn.XLOOKUP(D83,Products!A:A,Products!C:C,"") -> Beauty & Personal Care | L83: =_xlfn.XLOOKUP(C83,Customers!A:A,Customers!D:D,"") -> Chandigarh | M83: =_xlfn.XLOOKUP(C83,Customers!A:A,Customers!E:E,"") -> Small Business
A84: O000083 | B84: 45894 | C84: C0617 | D84: P057 | E84: 1 | F84: 0.2 | G84: 42988 | H84: 34390.4 | I84: 0.19 | J84: 5667.959105655823 | K84: =_xlfn.XLOOKUP(D84,Products!A:A,Products!C:C,"") -> Home Appliances | L84: =_xlfn.XLOOKUP(C84,Customers!A:A,Customers!D:D,"") -> Delhi | M84: =_xlfn.XLOOKUP(C84,Customers!A:A,Customers!E:E,"") -> Consumer
A85: O000084 | B85: 45838 | C85: C0474 | D85: P060 | E85: 2 | F85: 0.1 | G85: 1533 | H85: 2759.4 | I85: 0.16 | J85: 504.0916066078625 | K85: =_xlfn.XLOOKUP(D85,Products!A:A,Products!C:C,"") -> Technology | L85: =_xlfn.XLOOKUP(C85,Customers!A:A,Customers!D:D,"") -> Rajasthan | M85: =_xlfn.XLOOKUP(C85,Customers!A:A,Customers!E:E,"") -> Consumer
A86: O000085 | B86: 45968 | C86: C0059 | D86: P028 | E86: 2 | F86: 0.05 | G86: 7879 | H86: 14970.099999999999 | I86: 0.16 | J86: 2553.8331174760333 | K86: =_xlfn.XLOOKUP(D86,Products!A:A,Products!C:C,"") -> Technology | L86: =_xlfn.XLOOKUP(C86,Customers!A:A,Customers!D:D,"") -> Tamil Nadu | M86: =_xlfn.XLOOKUP(C86,Customers!A:A,Customers!E:E,"") -> Corporate
A87: O000086 | B87: 45694 | C87: C0589 | D87: P028 | E87: 2 | F87: 0.15 | G87: 7879 | H87: 13394.3 | I87: 0.16 | J87: 2380.093502219984 | K87: =_xlfn.XLOOKUP(D87,Products!A:A,Products!C:C,"") -> Technology | L87: =_xlfn.XLOOKUP(C87,Customers!A:A,Customers!D:D,"") -> West Bengal | M87: =_xlfn.XLOOKUP(C87,Customers!A:A,Customers!E:E,"") -> Consumer
A88: O000087 | B88: 45713 | C88: C0499 | D88: P046 | E88: 2 | F88: 0.05 | G88: 28530 | H88: 54207 | I88: 0.16 | J88: 9412.549382961875 | K88: =_xlfn.XLOOKUP(D88,Products!A:A,Products!C:C,"") -> Technology | L88: =_xlfn.XLOOKUP(C88,Customers!A:A,Customers!D:D,"") -> Tamil Nadu | M88: =_xlfn.XLOOKUP(C88,Customers!A:A,Customers!E:E,"") -> Consumer
A89: O000088 | B89: 45894 | C89: C0567 | D89: P071 | E89: 1 | F89: 0.1 | G89: 23441 | H89: 21096.9 | I89: 0.19 | J89: 3505.2688 | K89: =_xlfn.XLOOKUP(D89,Products!A:A,Products!C:C,"") -> Home Appliances | L89: =_xlfn.XLOOKUP(C89,Customers!A:A,Customers!D:D,"") -> West Bengal | M89: =_xlfn.XLOOKUP(C89,Customers!A:A,Customers!E:E,"") -> Corporate
A90: O000089 | B90: 46015 | C90: C0567 | D90: P067 | E90: 2 | F90: 0.1 | G90: 31519 | H90: 56734.200000000004 | I90: 0.19 | J90: 10628.887575106723 | K90: =_xlfn.XLOOKUP(D90,Products!A:A,Products!C:C,"") -> Home Appliances | L90: =_xlfn.XLOOKUP(C90,Customers!A:A,Customers!D:D,"") -> West Bengal | M90: =_xlfn.XLOOKUP(C90,Customers!A:A,Customers!E:E,"") -> Corporate
A91: O000090 | B91: 46006 | C91: C1153 | D91: P055 | E91: 4 | F91: 0 | G91: 38513 | H91: 154052 | I91: 0.19 | J91: 19256.96729034728 | K91: =_xlfn.XLOOKUP(D91,Products!A:A,Products!C:C,"") -> Home Appliances | L91: =_xlfn.XLOOKUP(C91,Customers!A:A,Customers!D:D,"") -> Uttar Pradesh | M91: =_xlfn.XLOOKUP(C91,Customers!A:A,Customers!E:E,"") -> Consumer
A92: O000091 | B92: 45854 | C92: C0904 | D92: P038 | E92: 2 | F92: 0.1 | G92: 9257 | H92: 16662.600000000002 | I92: 0.16 | J92: 2368.1032563091035 | K92: =_xlfn.XLOOKUP(D92,Products!A:A,Products!C:C,"") -> Technology | L92: =_xlfn.XLOOKUP(C92,Customers!A:A,Customers!D:D,"") -> Maharashtra | M92: =_xlfn.XLOOKUP(C92,Customers!A:A,Customers!E:E,"") -> Consumer
A93: O000092 | B93: 45730 | C93: C0383 | D93: P018 | E93: 1 | F93: 0.05 | G93: 4101 | H93: 3895.95 | I93: 0.16 | J93: 589.8974173302701 | K93: =_xlfn.XLOOKUP(D93,Products!A:A,Products!C:C,"") -> Technology | L93: =_xlfn.XLOOKUP(C93,Customers!A:A,Customers!D:D,"") -> Maharashtra | M93: =_xlfn.XLOOKUP(C93,Customers!A:A,Customers!E:E,"") -> Consumer
A94: O000093 | B94: 45716 | C94: C0085 | D94: P076 | E94: 3 | F94: 0 | G94: 36976 | H94: 110928 | I94: 0.28 | J94: 33493.19766979856 | K94: =_xlfn.XLOOKUP(D94,Products!A:A,Products!C:C,"") -> Office Supplies | L94: =_xlfn.XLOOKUP(C94,Customers!A:A,Customers!D:D,"") -> Gujarat | M94: =_xlfn.XLOOKUP(C94,Customers!A:A,Customers!E:E,"") -> Small Business
A95: O000094 | B95: 45897 | C95: C0627 | D95: P063 | E95: 1 | F95: 0.2 | G95: 11537 | H95: 9229.6 | I95: 0.22 | J95: 2195.955179111385 | K95: =_xlfn.XLOOKUP(D95,Products!A:A,Products!C:C,"") -> Furniture | L95: =_xlfn.XLOOKUP(C95,Customers!A:A,Customers!D:D,"") -> Telangana | M95: =_xlfn.XLOOKUP(C95,Customers!A:A,Customers!E:E,"") -> Consumer
A96: O000095 | B96: 45659 | C96: C0826 | D96: P005 | E96: 3 | F96: 0.1 | G96: 14854 | H96: 40105.8 | I96: 0.22 | J96: 7767.576519742067 | K96: =_xlfn.XLOOKUP(D96,Products!A:A,Products!C:C,"") -> Furniture | L96: =_xlfn.XLOOKUP(C96,Customers!A:A,Customers!D:D,"") -> Maharashtra | M96: =_xlfn.XLOOKUP(C96,Customers!A:A,Customers!E:E,"") -> Corporate
A97: O000096 | B97: 46017 | C97: C0293 | D97: P044 | E97: 1 | F97: 0.05 | G97: 41116 | H97: 39060.2 | I97: 0.19 | J97: 6363.015641578577 | K97: =_xlfn.XLOOKUP(D97,Products!A:A,Products!C:C,"") -> Home Appliances | L97: =_xlfn.XLOOKUP(C97,Customers!A:A,Customers!D:D,"") -> Chandigarh | M97: =_xlfn.XLOOKUP(C97,Customers!A:A,Customers!E:E,"") -> Consumer
A98: O000097 | B98: 45845 | C98: C1073 | D98: P029 | E98: 1 | F98: 0.1 | G98: 15711 | H98: 14139.9 | I98: 0.19 | J98: 3333.398006084881 | K98: =_xlfn.XLOOKUP(D98,Products!A:A,Products!C:C,"") -> Home Appliances | L98: =_xlfn.XLOOKUP(C98,Customers!A:A,Customers!D:D,"") -> Delhi | M98: =_xlfn.XLOOKUP(C98,Customers!A:A,Customers!E:E,"") -> Consumer
A99: O000098 | B99: 45964 | C99: C1091 | D99: P014 | E99: 1 | F99: 0.15 | G99: 34314 | H99: 29166.899999999998 | I99: 0.16 | J99: 4366.6701086163885 | K99: =_xlfn.XLOOKUP(D99,Products!A:A,Products!C:C,"") -> Technology | L99: =_xlfn.XLOOKUP(C99,Customers!A:A,Customers!D:D,"") -> Gujarat | M99: =_xlfn.XLOOKUP(C99,Customers!A:A,Customers!E:E,"") -> Consumer
A100: O000099 | B100: 45687 | C100: C0787 | D100: P058 | E100: 1 | F100: 0 | G100: 5109 | H100: 5109 | I100: 0.19 | J100: 991.1395992931658 | K100: =_xlfn.XLOOKUP(D100,Products!A:A,Products!C:C,"") -> Home Appliances | L100: =_xlfn.XLOOKUP(C100,Customers!A:A,Customers!D:D,"") -> Delhi | M100: =_xlfn.XLOOKUP(C100,Customers!A:A,Customers!E:E,"") -> Consumer
A101: O000100 | B101: 45924 | C101: C0129 | D101: P044 | E101: 2 | F101: 0.1 | G101: 41116 | H101: 74008.8 | I101: 0.19 | J101: 16095.707834244879 | K101: =_xlfn.XLOOKUP(D101,Products!A:A,Products!C:C,"") -> Home Appliances | L101: =_xlfn.XLOOKUP(C101,Customers!A:A,Customers!D:D,"") -> West Bengal | M101: =_xlfn.XLOOKUP(C101,Customers!A:A,Customers!E:E,"") -> Corporate
A102: O000101 | B102: 45765 | C102: C0029 | D102: P018 | E102: 1 | F102: 0.1 | G102: 4101 | H102: 3690.9 | I102: 0.16 | J102: 580.2738552702225 | K102: =_xlfn.XLOOKUP(D102,Products!A:A,Products!C:C,"") -> Technology | L102: =_xlfn.XLOOKUP(C102,Customers!A:A,Customers!D:D,"") -> Kerala | M102: =_xlfn.XLOOKUP(C102,Customers!A:A,Customers!E:E,"") -> Consumer
A103: O000102 | B103: 45989 | C103: C1143 | D103: P007 | E103: 3 | F103: 0.2 | G103: 32777 | H103: 78664.8 | I103: 0.19 | J103: 14528.751589410916 | K103: =_xlfn.XLOOKUP(D103,Products!A:A,Products!C:C,"") -> Home Appliances | L103: =_xlfn.XLOOKUP(C103,Customers!A:A,Customers!D:D,"") -> Karnataka | M103: =_xlfn.XLOOKUP(C103,Customers!A:A,Customers!E:E,"") -> Small Business
A104: O000103 | B104: 45747 | C104: C0692 | D104: P062 | E104: 2 | F104: 0.1 | G104: 40809 | H104: 73456.2 | I104: 0.19 | J104: 13145.970136191445 | K104: =_xlfn.XLOOKUP(D104,Products!A:A,Products!C:C,"") -> Home Appliances | L104: =_xlfn.XLOOKUP(C104,Customers!A:A,Customers!D:D,"") -> Delhi | M104: =_xlfn.XLOOKUP(C104,Customers!A:A,Customers!E:E,"") -> Small Business
...

Sheet Customers
A1: customer_id | B1: customer_name | C1: city | D1: state | E1: customer_segment
A2: C0001 | B2: Arjun Das | C2: Kolkata | D2: West Bengal | E2: Consumer
A3: C0002 | B3: Isha Sharma | C3: Hyderabad | D3: Telangana | E3: Consumer
A4: C0003 | B4: Rohan Kumar | C4: Lucknow | D4: Uttar Pradesh | E4: Corporate
A5: C0004 | B5: Varun Gupta | C5: Ahmedabad | D5: Gujarat | E5: Corporate
A6: C0005 | B6: Meera Das | C6: Chennai | D6: Tamil Nadu | E6: Consumer
A7: C0006 | B7: Rohan Kumar | C7: Kolkata | D7: West Bengal | E7: Corporate
A8: C0007 | B8: Vikram Iyer | C8: Kochi | D8: Kerala | E8: Consumer
A9: C0008 | B9: Aarav Bhat | C9: Delhi | D9: Delhi | E9: Corporate
A10: C0009 | B10: Arjun Singh | C10: Kolkata | D10: West Bengal | E10: Corporate
A11: C0010 | B11: Meera Nair | C11: Lucknow | D11: Uttar Pradesh | E11: Consumer
A12: C0011 | B12: Aarav Kapoor | C12: Lucknow | D12: Uttar Pradesh | E12: Consumer
... A1201: C1200 | B1201: Kavya Joshi | C1201: Ahmedabad | D1201: Gujarat | E1201: Corporate

Sheet Products
A1: Column1 | B1: Column2 | C1: Column3 | D1: Column4
A2: product_id | B2: product_name | C2: category | D2: sub_category
A3: P001 | B3: Accessories Product 001 | C3: Technology | D3: Accessories
A4: P002 | B4: Small Appliances Product 002 | C4: Home Appliances | D4: Small Appliances
A5: P003 | B5: Accessories Product 003 | C5: Technology | D5: Accessories
A6: P004 | B6: Laptops Product 004 | C6: Technology | D6: Laptops
A7: P005 | B7: Office Furniture Product 005 | C7: Furniture | D7: Office Furniture
A8: P006 | B8: Chairs Product 006 | C8: Furniture | D8: Chairs
A9: P007 | B9: Lighting Product 007 | C9: Home Appliances | D9: Lighting
A10: P008 | B10: Kitchen Product 008 | C10: Home Appliances | D10: Kitchen
A11: P009 | B11: Organizers Product 009 | C11: Office Supplies | D11: Organizers
A12: P010 | B12: Writing Product 010 | C12: Office Supplies | D12: Writing
... A82: P080 | B82: Chairs Product 080 | C82: Furniture | D82: Chairs

Sheet Sheet3
A1: E-commerce Sales Analysis
A2: Total Orders | B2: =COUNTA(_xlfn.UNIQUE(orderstable[order_id])) -> 11985 | E2: Row Labels | F2: Count of sales | G2: Count of profit
A3: Total Units Sold | B3: =SUM(orderstable[quantity]) -> 24122 | E3: Beauty & Personal Care | F3: 867 | G3: 867
A4: Total Sales | B4: =SUM(orderstable[sales]) -> 4.312538e+08 | E4: Furniture | F4: 2116 | G4: 2116
A5: Total Profit | B5: =SUM(orderstable[profit]) -> 5819150.4 | E5: Home Appliances | F5: 4194 | G5: 4194
A6: Profit Margin | B6: =B5/B4 -> 0.013493563 | E6: Office Supplies | F6: 1604 | G6: 1604
E7: Technology | F7: 3205 | G7: 3205
E8: Grand Total | F8: 11986 | G8: 11986
A9: Category | B9: sales | C9: profit
A10: Home Appliances
A11: Technology
A12: Furniture
A13: Office Supplies
A14: Beauty & Personal Care
